[{"timestamp":"2023-06-19T00:42:13.818Z","count":0,"uniques":0},{"timestamp":"2023-06-20T00:40:47.211Z","count":0,"uniques":0},{"timestamp":"2023-06-21T00:41:52.694Z","count":0,"uniques":0},{"timestamp":"2023-06-22T00:42:19.974Z","count":0,"uniques":0},{"timestamp":"2023-06-23T00:45:50.408Z","count":0,"uniques":0},{"timestamp":"2023-06-24T00:47:24.199Z","count":0,"uniques":0},{"timestamp":"2023-06-25T00:51:50.231Z","count":0,"uniques":0},{"timestamp":"2023-06-26T00:47:03.752Z","count":0,"uniques":0},{"timestamp":"2023-06-27T00:47:25.358Z","count":0,"uniques":0},{"timestamp":"2023-06-28T00:47:01.284Z","count":0,"uniques":0},{"timestamp":"2023-06-29T00:45:34.285Z","count":0,"uniques":0},{"timestamp":"2023-06-30T00:44:23.060Z","count":0,"uniques":0},{"timestamp":"2023-07-01T00:51:39.066Z","count":0,"uniques":0},{"timestamp":"2023-07-02T00:48:43.606Z","count":0,"uniques":0},{"timestamp":"2023-07-03T00:47:11.878Z","count":0,"uniques":0},{"timestamp":"2023-07-04T00:48:32.417Z","count":0,"uniques":0},{"timestamp":"2023-07-05T00:47:14.890Z","count":0,"uniques":0},{"timestamp":"2023-07-06T00:48:00.871Z","count":0,"uniques":0},{"timestamp":"2023-07-07T00:49:05.712Z","count":0,"uniques":0},{"timestamp":"2023-07-08T00:47:05.432Z","count":0,"uniques":0},{"timestamp":"2023-07-09T00:50:41.175Z","count":0,"uniques":0},{"timestamp":"2023-07-10T00:47:04.500Z","count":0,"uniques":0},{"timestamp":"2023-07-11T00:41:51.233Z","count":0,"uniques":0},{"timestamp":"2023-07-12T00:47:25.567Z","count":0,"uniques":0},{"timestamp":"2023-07-13T00:47:15.920Z","count":0,"uniques":0},{"timestamp":"2023-07-14T00:48:40.610Z","count":0,"uniques":0},{"timestamp":"2023-07-15T00:46:43.145Z","count":0,"uniques":0},{"timestamp":"2023-07-16T00:53:11.197Z","count":0,"uniques":0},{"timestamp":"2023-07-17T00:49:30.043Z","count":0,"uniques":0},{"timestamp":"2023-07-18T01:05:10.081Z","count":0,"uniques":0},{"timestamp":"2023-07-19T01:16:09.884Z","count":0,"uniques":0}]
