[{"timestamp":"2025-01-09T00:07:24.305Z","count":0,"uniques":0},{"timestamp":"2025-01-10T00:07:15.428Z","count":0,"uniques":0},{"timestamp":"2025-01-11T00:07:01.851Z","count":0,"uniques":0},{"timestamp":"2025-01-12T00:08:10.488Z","count":0,"uniques":0},{"timestamp":"2025-01-13T00:07:55.407Z","count":0,"uniques":0},{"timestamp":"2025-01-14T00:07:12.762Z","count":0,"uniques":0},{"timestamp":"2025-01-15T00:07:12.762Z","count":0,"uniques":0},{"timestamp":"2025-01-16T00:07:06.032Z","count":0,"uniques":0},{"timestamp":"2025-01-17T00:07:34.226Z","count":0,"uniques":0},{"timestamp":"2025-01-18T00:07:14.375Z","count":0,"uniques":0},{"timestamp":"2025-01-19T00:07:49.056Z","count":0,"uniques":0},{"timestamp":"2025-01-20T00:07:42.090Z","count":0,"uniques":0},{"timestamp":"2025-01-21T00:06:57.932Z","count":0,"uniques":0},{"timestamp":"2025-01-22T00:07:19.624Z","count":0,"uniques":0},{"timestamp":"2025-01-23T00:06:50.739Z","count":0,"uniques":0},{"timestamp":"2025-01-24T00:06:56.312Z","count":0,"uniques":0},{"timestamp":"2025-01-25T00:06:57.741Z","count":0,"uniques":0},{"timestamp":"2025-01-26T00:07:29.883Z","count":0,"uniques":0},{"timestamp":"2025-01-27T00:07:30.541Z","count":0,"uniques":0},{"timestamp":"2025-01-28T00:06:52.158Z","count":0,"uniques":0},{"timestamp":"2025-01-29T00:07:12.527Z","count":0,"uniques":0},{"timestamp":"2025-01-30T00:07:08.914Z","count":0,"uniques":0},{"timestamp":"2025-01-31T00:06:58.228Z","count":0,"uniques":0},{"timestamp":"2025-02-01T00:07:23.771Z","count":0,"uniques":0},{"timestamp":"2025-02-02T00:07:51.570Z","count":0,"uniques":0},{"timestamp":"2025-02-03T00:07:46.791Z","count":0,"uniques":0},{"timestamp":"2025-02-04T00:07:30.881Z","count":0,"uniques":0},{"timestamp":"2025-02-05T00:07:10.770Z","count":0,"uniques":0},{"timestamp":"2025-02-06T00:07:20.168Z","count":0,"uniques":0},{"timestamp":"2025-02-07T00:07:23.228Z","count":0,"uniques":0},{"timestamp":"2025-02-08T00:06:51.452Z","count":0,"uniques":0},{"timestamp":"2025-02-09T00:08:01.273Z","count":0,"uniques":0},{"timestamp":"2025-02-10T00:07:20.280Z","count":0,"uniques":0},{"timestamp":"2025-02-11T00:06:58.721Z","count":0,"uniques":0},{"timestamp":"2025-02-12T00:06:56.559Z","count":0,"uniques":0},{"timestamp":"2025-02-13T00:07:16.227Z","count":0,"uniques":0},{"timestamp":"2025-02-14T00:07:26.637Z","count":0,"uniques":0},{"timestamp":"2025-02-15T00:06:59.820Z","count":0,"uniques":0},{"timestamp":"2025-02-16T00:07:44.783Z","count":0,"uniques":0},{"timestamp":"2025-02-17T00:07:50.111Z","count":0,"uniques":0},{"timestamp":"2025-02-18T00:07:26.677Z","count":0,"uniques":0},{"timestamp":"2025-02-19T00:07:02.505Z","count":0,"uniques":0},{"timestamp":"2025-02-20T00:07:09.674Z","count":0,"uniques":0},{"timestamp":"2025-02-21T00:07:06.352Z","count":0,"uniques":0},{"timestamp":"2025-02-22T00:07:04.507Z","count":0,"uniques":0},{"timestamp":"2025-02-23T00:07:57.977Z","count":0,"uniques":0},{"timestamp":"2025-02-24T00:07:30.114Z","count":0,"uniques":0},{"timestamp":"2025-02-25T00:00:00.000Z","count":2,"uniques":1},{"timestamp":"2025-02-26T00:07:18.422Z","count":0,"uniques":0},{"timestamp":"2025-02-27T00:00:00.000Z","count":1,"uniques":1},{"timestamp":"2025-02-28T00:07:31.540Z","count":0,"uniques":0},{"timestamp":"2025-03-01T00:08:06.631Z","count":0,"uniques":0},{"timestamp":"2025-03-02T00:07:37.683Z","count":0,"uniques":0},{"timestamp":"2025-03-03T00:07:34.880Z","count":0,"uniques":0},{"timestamp":"2025-03-04T00:07:46.028Z","count":0,"uniques":0},{"timestamp":"2025-03-05T00:07:44.226Z","count":0,"uniques":0},{"timestamp":"2025-03-06T00:07:18.132Z","count":0,"uniques":0},{"timestamp":"2025-03-07T00:07:45.309Z","count":0,"uniques":0},{"timestamp":"2025-03-08T00:06:55.478Z","count":0,"uniques":0},{"timestamp":"2025-03-09T00:07:05.402Z","count":0,"uniques":0},{"timestamp":"2025-03-10T00:06:52.647Z","count":0,"uniques":0},{"timestamp":"2025-03-11T00:07:55.626Z","count":0,"uniques":0},{"timestamp":"2025-03-12T00:07:31.763Z","count":0,"uniques":0},{"timestamp":"2025-03-13T00:07:58.629Z","count":0,"uniques":0},{"timestamp":"2025-03-14T00:07:26.876Z","count":0,"uniques":0},{"timestamp":"2025-03-15T00:07:18.258Z","count":0,"uniques":0},{"timestamp":"2025-03-16T00:07:44.393Z","count":0,"uniques":0},{"timestamp":"2025-03-17T00:00:00.000Z","count":2,"uniques":1},{"timestamp":"2025-03-18T00:07:57.661Z","count":0,"uniques":0},{"timestamp":"2025-03-19T00:07:40.846Z","count":0,"uniques":0},{"timestamp":"2025-03-20T00:07:29.206Z","count":0,"uniques":0},{"timestamp":"2025-03-21T00:07:35.382Z","count":0,"uniques":0},{"timestamp":"2025-03-22T00:07:42.109Z","count":0,"uniques":0},{"timestamp":"2025-03-23T00:07:39.811Z","count":0,"uniques":0},{"timestamp":"2025-03-24T00:07:39.322Z","count":0,"uniques":0},{"timestamp":"2025-03-25T00:07:40.147Z","count":0,"uniques":0},{"timestamp":"2025-03-26T00:07:42.066Z","count":0,"uniques":0},{"timestamp":"2025-03-27T00:08:00.768Z","count":0,"uniques":0},{"timestamp":"2025-03-28T00:07:51.118Z","count":0,"uniques":0},{"timestamp":"2025-03-29T00:07:30.105Z","count":0,"uniques":0},{"timestamp":"2025-03-30T00:07:40.282Z","count":0,"uniques":0},{"timestamp":"2025-03-31T00:07:48.649Z","count":0,"uniques":0},{"timestamp":"2025-04-01T00:08:05.259Z","count":0,"uniques":0},{"timestamp":"2025-04-02T00:07:39.543Z","count":0,"uniques":0},{"timestamp":"2025-04-03T00:07:52.422Z","count":0,"uniques":0},{"timestamp":"2025-04-04T00:07:55.718Z","count":0,"uniques":0},{"timestamp":"2025-04-05T00:07:52.757Z","count":0,"uniques":0},{"timestamp":"2025-04-06T00:07:30.162Z","count":0,"uniques":0},{"timestamp":"2025-04-07T00:07:44.187Z","count":0,"uniques":0},{"timestamp":"2025-04-08T00:07:37.639Z","count":0,"uniques":0},{"timestamp":"2025-04-09T00:08:04.627Z","count":0,"uniques":0},{"timestamp":"2025-04-10T00:07:52.773Z","count":0,"uniques":0},{"timestamp":"2025-04-11T00:07:54.186Z","count":0,"uniques":0},{"timestamp":"2025-04-12T00:07:59.236Z","count":0,"uniques":0},{"timestamp":"2025-04-13T00:32:07.550Z","count":0,"uniques":0},{"timestamp":"2025-04-14T00:07:51.387Z","count":0,"uniques":0},{"timestamp":"2025-04-15T00:07:50.434Z","count":0,"uniques":0},{"timestamp":"2025-04-16T02:03:31.524Z","count":0,"uniques":0},{"timestamp":"2025-04-17T02:03:31.524Z","count":0,"uniques":0},{"timestamp":"2025-04-18T02:03:31.524Z","count":0,"uniques":0},{"timestamp":"2025-04-19T02:03:31.524Z","count":0,"uniques":0},{"timestamp":"2025-04-20T02:03:31.524Z","count":0,"uniques":0},{"timestamp":"2025-04-21T02:03:31.524Z","count":0,"uniques":0},{"timestamp":"2025-04-22T02:03:31.524Z","count":0,"uniques":0},{"timestamp":"2025-04-23T02:03:31.524Z","count":0,"uniques":0},{"timestamp":"2025-04-24T02:03:31.524Z","count":0,"uniques":0},{"timestamp":"2025-04-25T02:03:31.524Z","count":0,"uniques":0},{"timestamp":"2025-04-26T02:03:31.524Z","count":0,"uniques":0},{"timestamp":"2025-04-27T02:03:31.524Z","count":0,"uniques":0},{"timestamp":"2025-04-28T02:03:31.524Z","count":0,"uniques":0},{"timestamp":"2025-04-29T02:03:31.524Z","count":0,"uniques":0},{"timestamp":"2025-04-30T02:03:31.524Z","count":0,"uniques":0},{"timestamp":"2025-05-01T02:03:31.524Z","count":0,"uniques":0},{"timestamp":"2025-05-02T02:03:31.524Z","count":0,"uniques":0},{"timestamp":"2025-05-03T02:03:31.524Z","count":0,"uniques":0},{"timestamp":"2025-05-04T02:03:31.524Z","count":0,"uniques":0},{"timestamp":"2025-05-05T02:03:31.524Z","count":0,"uniques":0},{"timestamp":"2025-05-06T02:03:31.524Z","count":0,"uniques":0},{"timestamp":"2025-05-07T02:03:31.524Z","count":0,"uniques":0},{"timestamp":"2025-05-08T02:03:31.524Z","count":0,"uniques":0},{"timestamp":"2025-05-09T02:03:31.524Z","count":0,"uniques":0},{"timestamp":"2025-05-10T02:03:31.524Z","count":0,"uniques":0},{"timestamp":"2025-05-11T02:03:31.524Z","count":0,"uniques":0},{"timestamp":"2025-05-12T02:03:31.524Z","count":0,"uniques":0},{"timestamp":"2025-05-13T02:03:31.524Z","count":0,"uniques":0},{"timestamp":"2025-05-14T02:03:31.524Z","count":0,"uniques":0},{"timestamp":"2025-05-15T02:03:31.524Z","count":0,"uniques":0},{"timestamp":"2025-05-16T02:03:31.524Z","count":0,"uniques":0},{"timestamp":"2025-05-17T02:03:31.524Z","count":0,"uniques":0},{"timestamp":"2025-05-18T02:03:31.524Z","count":0,"uniques":0},{"timestamp":"2025-05-19T02:03:31.524Z","count":0,"uniques":0},{"timestamp":"2025-05-20T02:03:31.524Z","count":0,"uniques":0},{"timestamp":"2025-05-21T02:03:31.524Z","count":0,"uniques":0},{"timestamp":"2025-05-22T02:03:31.524Z","count":0,"uniques":0},{"timestamp":"2025-05-23T02:03:31.524Z","count":0,"uniques":0},{"timestamp":"2025-05-24T02:03:31.524Z","count":0,"uniques":0},{"timestamp":"2025-05-25T02:03:31.524Z","count":0,"uniques":0},{"timestamp":"2025-05-26T02:03:31.524Z","count":0,"uniques":0},{"timestamp":"2025-05-27T02:03:31.524Z","count":0,"uniques":0},{"timestamp":"2025-05-28T02:03:31.524Z","count":0,"uniques":0},{"timestamp":"2025-05-29T02:03:31.524Z","count":0,"uniques":0},{"timestamp":"2025-05-30T02:03:31.524Z","count":0,"uniques":0},{"timestamp":"2025-05-31T02:03:31.524Z","count":0,"uniques":0},{"timestamp":"2025-06-01T02:03:31.524Z","count":0,"uniques":0},{"timestamp":"2025-06-02T02:03:31.524Z","count":0,"uniques":0},{"timestamp":"2025-06-03T02:03:31.524Z","count":0,"uniques":0},{"timestamp":"2025-06-04T02:03:31.524Z","count":0,"uniques":0},{"timestamp":"2025-06-05T02:03:31.524Z","count":0,"uniques":0},{"timestamp":"2025-06-06T02:03:31.524Z","count":0,"uniques":0},{"timestamp":"2025-06-07T02:03:31.524Z","count":0,"uniques":0},{"timestamp":"2025-06-08T02:03:31.524Z","count":0,"uniques":0},{"timestamp":"2025-06-09T02:03:31.524Z","count":0,"uniques":0},{"timestamp":"2025-06-10T02:03:31.524Z","count":0,"uniques":0},{"timestamp":"2025-06-11T02:03:31.524Z","count":0,"uniques":0},{"timestamp":"2025-06-12T02:03:31.524Z","count":0,"uniques":0},{"timestamp":"2025-06-13T02:03:31.524Z","count":0,"uniques":0},{"timestamp":"2025-06-14T02:03:31.524Z","count":0,"uniques":0},{"timestamp":"2025-06-15T02:03:31.524Z","count":0,"uniques":0},{"timestamp":"2025-06-16T02:03:31.524Z","count":0,"uniques":0},{"timestamp":"2025-06-17T02:03:31.524Z","count":0,"uniques":0},{"timestamp":"2025-06-18T02:03:31.524Z","count":0,"uniques":0},{"timestamp":"2025-06-19T02:03:31.524Z","count":0,"uniques":0},{"timestamp":"2025-06-20T02:03:31.524Z","count":0,"uniques":0},{"timestamp":"2025-06-21T02:03:31.524Z","count":0,"uniques":0},{"timestamp":"2025-06-22T02:03:31.524Z","count":0,"uniques":0},{"timestamp":"2025-06-23T02:03:31.524Z","count":0,"uniques":0},{"timestamp":"2025-06-24T02:03:31.524Z","count":0,"uniques":0},{"timestamp":"2025-06-25T02:03:31.524Z","count":0,"uniques":0},{"timestamp":"2025-06-26T02:03:31.524Z","count":0,"uniques":0},{"timestamp":"2025-06-27T02:03:31.524Z","count":0,"uniques":0},{"timestamp":"2025-06-28T02:03:31.524Z","count":0,"uniques":0},{"timestamp":"2025-06-29T02:03:31.524Z","count":0,"uniques":0},{"timestamp":"2025-06-30T02:03:31.524Z","count":0,"uniques":0},{"timestamp":"2025-07-01T02:03:31.524Z","count":0,"uniques":0},{"timestamp":"2025-07-02T02:03:31.524Z","count":0,"uniques":0},{"timestamp":"2025-07-03T02:03:31.524Z","count":0,"uniques":0},{"timestamp":"2025-07-04T02:03:31.524Z","count":0,"uniques":0},{"timestamp":"2025-07-05T02:03:31.524Z","count":0,"uniques":0},{"timestamp":"2025-07-06T02:03:31.524Z","count":0,"uniques":0},{"timestamp":"2025-07-07T02:03:31.524Z","count":0,"uniques":0},{"timestamp":"2025-07-08T02:03:31.524Z","count":0,"uniques":0},{"timestamp":"2025-07-09T02:03:31.524Z","count":0,"uniques":0},{"timestamp":"2025-07-10T02:03:31.524Z","count":0,"uniques":0},{"timestamp":"2025-07-11T02:03:31.524Z","count":0,"uniques":0},{"timestamp":"2025-07-12T02:03:31.524Z","count":0,"uniques":0},{"timestamp":"2025-07-13T02:03:31.524Z","count":0,"uniques":0},{"timestamp":"2025-07-14T02:03:31.524Z","count":0,"uniques":0},{"timestamp":"2025-07-15T02:03:31.524Z","count":0,"uniques":0},{"timestamp":"2025-07-16T02:03:31.524Z","count":0,"uniques":0},{"timestamp":"2025-07-17T02:03:31.524Z","count":0,"uniques":0},{"timestamp":"2025-07-18T02:03:31.524Z","count":0,"uniques":0},{"timestamp":"2025-07-19T02:03:31.524Z","count":0,"uniques":0},{"timestamp":"2025-07-20T02:03:31.524Z","count":0,"uniques":0},{"timestamp":"2025-07-21T02:03:31.524Z","count":0,"uniques":0},{"timestamp":"2025-07-22T02:03:31.524Z","count":0,"uniques":0},{"timestamp":"2025-07-23T02:03:31.524Z","count":0,"uniques":0},{"timestamp":"2025-07-24T02:03:31.524Z","count":0,"uniques":0},{"timestamp":"2025-07-25T02:03:31.524Z","count":0,"uniques":0},{"timestamp":"2025-07-26T02:03:31.524Z","count":0,"uniques":0},{"timestamp":"2025-07-27T02:03:31.524Z","count":0,"uniques":0},{"timestamp":"2025-07-28T02:03:31.524Z","count":0,"uniques":0},{"timestamp":"2025-07-29T02:03:31.524Z","count":0,"uniques":0},{"timestamp":"2025-07-30T02:03:31.524Z","count":0,"uniques":0},{"timestamp":"2025-07-31T02:03:31.524Z","count":0,"uniques":0},{"timestamp":"2025-08-01T02:03:31.524Z","count":0,"uniques":0},{"timestamp":"2025-08-02T02:03:31.524Z","count":0,"uniques":0},{"timestamp":"2025-08-03T00:08:44.570Z","count":0,"uniques":0},{"timestamp":"2025-08-04T00:08:49.066Z","count":0,"uniques":0},{"timestamp":"2025-08-05T00:08:32.443Z","count":0,"uniques":0},{"timestamp":"2025-08-06T00:08:20.553Z","count":0,"uniques":0},{"timestamp":"2025-08-07T00:08:38.373Z","count":0,"uniques":0},{"timestamp":"2025-08-08T00:08:40.305Z","count":0,"uniques":0},{"timestamp":"2025-08-09T00:08:02.188Z","count":0,"uniques":0},{"timestamp":"2025-08-10T00:08:54.839Z","count":0,"uniques":0},{"timestamp":"2025-08-11T00:08:41.487Z","count":0,"uniques":0},{"timestamp":"2025-08-12T00:08:07.421Z","count":0,"uniques":0},{"timestamp":"2025-08-13T00:08:10.091Z","count":0,"uniques":0},{"timestamp":"2025-08-14T00:08:05.489Z","count":0,"uniques":0},{"timestamp":"2025-08-15T00:08:23.218Z","count":0,"uniques":0},{"timestamp":"2025-08-16T00:07:34.525Z","count":0,"uniques":0},{"timestamp":"2025-08-17T00:08:29.591Z","count":0,"uniques":0},{"timestamp":"2025-08-18T00:08:25.758Z","count":0,"uniques":0},{"timestamp":"2025-08-19T00:07:52.480Z","count":0,"uniques":0},{"timestamp":"2025-08-20T00:07:56.960Z","count":0,"uniques":0},{"timestamp":"2025-08-21T00:06:58.986Z","count":0,"uniques":0},{"timestamp":"2025-08-22T00:08:03.853Z","count":0,"uniques":0},{"timestamp":"2025-08-23T00:07:39.986Z","count":0,"uniques":0},{"timestamp":"2025-08-24T00:08:03.349Z","count":0,"uniques":0},{"timestamp":"2025-08-25T00:07:53.030Z","count":0,"uniques":0},{"timestamp":"2025-08-26T00:07:41.120Z","count":0,"uniques":0},{"timestamp":"2025-08-27T00:07:30.853Z","count":0,"uniques":0},{"timestamp":"2025-08-28T00:07:14.191Z","count":0,"uniques":0},{"timestamp":"2025-08-29T00:07:15.580Z","count":0,"uniques":0},{"timestamp":"2025-08-30T00:07:10.104Z","count":0,"uniques":0},{"timestamp":"2025-08-31T00:08:32.814Z","count":0,"uniques":0},{"timestamp":"2025-09-01T00:08:24.780Z","count":0,"uniques":0},{"timestamp":"2025-09-02T00:07:26.639Z","count":0,"uniques":0},{"timestamp":"2025-09-03T00:07:34.465Z","count":0,"uniques":0},{"timestamp":"2025-09-04T00:07:20.452Z","count":0,"uniques":0},{"timestamp":"2025-09-05T00:07:36.003Z","count":0,"uniques":0},{"timestamp":"2025-09-06T00:07:23.337Z","count":0,"uniques":0},{"timestamp":"2025-09-07T00:07:52.288Z","count":0,"uniques":0},{"timestamp":"2025-09-08T00:07:44.200Z","count":0,"uniques":0},{"timestamp":"2025-09-09T00:07:43.149Z","count":0,"uniques":0},{"timestamp":"2025-09-10T00:06:56.887Z","count":0,"uniques":0},{"timestamp":"2025-09-11T00:07:17.667Z","count":0,"uniques":0},{"timestamp":"2025-09-12T00:07:34.804Z","count":0,"uniques":0},{"timestamp":"2025-09-13T00:06:42.620Z","count":0,"uniques":0},{"timestamp":"2025-09-14T00:08:03.473Z","count":0,"uniques":0},{"timestamp":"2025-09-15T00:08:10.454Z","count":0,"uniques":0},{"timestamp":"2025-09-16T00:07:33.217Z","count":0,"uniques":0},{"timestamp":"2025-09-17T00:07:41.691Z","count":0,"uniques":0},{"timestamp":"2025-09-18T00:07:37.934Z","count":0,"uniques":0},{"timestamp":"2025-09-19T00:07:42.513Z","count":0,"uniques":0},{"timestamp":"2025-09-20T00:06:59.695Z","count":0,"uniques":0},{"timestamp":"2025-09-21T00:00:00.000Z","count":3,"uniques":1},{"timestamp":"2025-09-22T00:07:52.373Z","count":0,"uniques":0},{"timestamp":"2025-09-23T00:07:40.067Z","count":0,"uniques":0},{"timestamp":"2025-09-24T00:07:58.154Z","count":0,"uniques":0},{"timestamp":"2025-09-25T00:07:37.756Z","count":0,"uniques":0},{"timestamp":"2025-09-26T00:07:49.061Z","count":0,"uniques":0},{"timestamp":"2025-09-27T00:06:50.100Z","count":0,"uniques":0},{"timestamp":"2025-09-28T00:08:14.268Z","count":0,"uniques":0},{"timestamp":"2025-09-29T00:08:00.594Z","count":0,"uniques":0},{"timestamp":"2025-09-30T00:08:02.847Z","count":0,"uniques":0},{"timestamp":"2025-10-01T00:08:16.544Z","count":0,"uniques":0},{"timestamp":"2025-10-02T00:07:31.402Z","count":0,"uniques":0},{"timestamp":"2025-10-03T00:07:27.449Z","count":0,"uniques":0},{"timestamp":"2025-10-04T00:07:50.804Z","count":0,"uniques":0},{"timestamp":"2025-10-05T00:07:56.810Z","count":0,"uniques":0},{"timestamp":"2025-10-06T00:07:39.823Z","count":0,"uniques":0},{"timestamp":"2025-10-07T00:07:59.201Z","count":0,"uniques":0},{"timestamp":"2025-10-08T00:07:30.552Z","count":0,"uniques":0},{"timestamp":"2025-10-09T00:07:34.361Z","count":0,"uniques":0},{"timestamp":"2025-10-10T00:08:09.013Z","count":0,"uniques":0},{"timestamp":"2025-10-11T00:07:32.119Z","count":0,"uniques":0},{"timestamp":"2025-10-12T00:07:47.815Z","count":0,"uniques":0},{"timestamp":"2025-10-13T00:07:52.593Z","count":0,"uniques":0},{"timestamp":"2025-10-14T00:07:32.241Z","count":0,"uniques":0},{"timestamp":"2025-10-15T00:07:38.961Z","count":0,"uniques":0},{"timestamp":"2025-10-16T00:07:58.134Z","count":0,"uniques":0},{"timestamp":"2025-10-17T00:07:52.005Z","count":0,"uniques":0},{"timestamp":"2025-10-18T00:07:32.195Z","count":0,"uniques":0},{"timestamp":"2025-10-19T00:08:16.322Z","count":0,"uniques":0},{"timestamp":"2025-10-20T00:07:44.082Z","count":0,"uniques":0},{"timestamp":"2025-10-21T00:08:08.862Z","count":0,"uniques":0},{"timestamp":"2025-10-22T00:08:06.377Z","count":0,"uniques":0},{"timestamp":"2025-10-23T00:07:58.565Z","count":0,"uniques":0},{"timestamp":"2025-10-24T00:06:55.428Z","count":0,"uniques":0},{"timestamp":"2025-10-25T00:07:39.260Z","count":0,"uniques":0},{"timestamp":"2025-10-26T00:08:08.541Z","count":0,"uniques":0},{"timestamp":"2025-10-27T00:08:10.021Z","count":0,"uniques":0},{"timestamp":"2025-10-28T00:07:36.508Z","count":0,"uniques":0},{"timestamp":"2025-10-29T00:07:55.672Z","count":0,"uniques":0},{"timestamp":"2025-10-30T00:08:08.096Z","count":0,"uniques":0},{"timestamp":"2025-10-31T00:07:45.204Z","count":0,"uniques":0},{"timestamp":"2025-11-01T00:08:01.891Z","count":0,"uniques":0},{"timestamp":"2025-11-02T00:08:12.714Z","count":0,"uniques":0},{"timestamp":"2025-11-03T00:07:46.005Z","count":0,"uniques":0},{"timestamp":"2025-11-04T00:07:39.145Z","count":0,"uniques":0},{"timestamp":"2025-11-05T00:07:51.264Z","count":0,"uniques":0},{"timestamp":"2025-11-06T00:07:39.419Z","count":0,"uniques":0},{"timestamp":"2025-11-07T00:07:48.071Z","count":0,"uniques":0},{"timestamp":"2025-11-08T00:07:44.950Z","count":0,"uniques":0},{"timestamp":"2025-11-09T00:08:02.534Z","count":0,"uniques":0},{"timestamp":"2025-11-10T00:00:00.000Z","count":1,"uniques":1},{"timestamp":"2025-11-11T00:08:05.008Z","count":0,"uniques":0},{"timestamp":"2025-11-12T00:08:14.910Z","count":0,"uniques":0},{"timestamp":"2025-11-13T00:07:51.796Z","count":0,"uniques":0},{"timestamp":"2025-11-14T00:07:48.600Z","count":0,"uniques":0},{"timestamp":"2025-11-15T00:07:56.470Z","count":0,"uniques":0},{"timestamp":"2025-11-16T00:07:51.918Z","count":0,"uniques":0},{"timestamp":"2025-11-17T00:07:45.747Z","count":0,"uniques":0},{"timestamp":"2025-11-18T00:07:56.934Z","count":0,"uniques":0},{"timestamp":"2025-11-19T00:08:00.376Z","count":0,"uniques":0},{"timestamp":"2025-11-20T00:07:42.196Z","count":0,"uniques":0},{"timestamp":"2025-11-21T00:07:52.351Z","count":0,"uniques":0},{"timestamp":"2025-11-22T00:07:47.816Z","count":0,"uniques":0},{"timestamp":"2025-11-23T00:08:13.897Z","count":0,"uniques":0},{"timestamp":"2025-11-24T00:00:00.000Z","count":1,"uniques":1},{"timestamp":"2025-11-25T00:06:59.179Z","count":0,"uniques":0},{"timestamp":"2025-11-26T00:08:00.653Z","count":0,"uniques":0},{"timestamp":"2025-11-27T00:08:03.067Z","count":0,"uniques":0},{"timestamp":"2025-11-28T00:08:08.422Z","count":0,"uniques":0},{"timestamp":"2025-11-29T00:07:29.839Z","count":0,"uniques":0},{"timestamp":"2025-11-30T00:08:19.092Z","count":0,"uniques":0},{"timestamp":"2025-12-01T00:09:14.840Z","count":0,"uniques":0},{"timestamp":"2025-12-02T00:08:11.763Z","count":0,"uniques":0},{"timestamp":"2025-12-03T00:08:11.567Z","count":0,"uniques":0},{"timestamp":"2025-12-04T00:08:08.702Z","count":0,"uniques":0},{"timestamp":"2025-12-05T00:07:55.758Z","count":0,"uniques":0},{"timestamp":"2025-12-06T00:07:38.305Z","count":0,"uniques":0},{"timestamp":"2025-12-07T00:08:09.337Z","count":0,"uniques":0},{"timestamp":"2025-12-08T00:08:29.046Z","count":0,"uniques":0},{"timestamp":"2025-12-09T00:08:02.166Z","count":0,"uniques":0},{"timestamp":"2025-12-10T00:07:59.829Z","count":0,"uniques":0},{"timestamp":"2025-12-11T00:08:16.194Z","count":0,"uniques":0},{"timestamp":"2025-12-12T00:08:13.355Z","count":0,"uniques":0},{"timestamp":"2025-12-13T00:07:54.159Z","count":0,"uniques":0},{"timestamp":"2025-12-14T00:08:23.756Z","count":0,"uniques":0},{"timestamp":"2025-12-15T00:08:24.272Z","count":0,"uniques":0},{"timestamp":"2025-12-16T00:08:39.191Z","count":0,"uniques":0},{"timestamp":"2025-12-17T00:07:12.289Z","count":0,"uniques":0},{"timestamp":"2025-12-18T00:07:26.597Z","count":0,"uniques":0},{"timestamp":"2025-12-19T00:09:04.722Z","count":0,"uniques":0},{"timestamp":"2025-12-20T00:07:55.277Z","count":0,"uniques":0},{"timestamp":"2025-12-21T00:08:20.782Z","count":0,"uniques":0},{"timestamp":"2025-12-22T00:08:17.151Z","count":0,"uniques":0},{"timestamp":"2025-12-23T00:07:55.816Z","count":0,"uniques":0},{"timestamp":"2025-12-24T00:08:05.612Z","count":0,"uniques":0},{"timestamp":"2025-12-25T00:07:58.531Z","count":0,"uniques":0},{"timestamp":"2025-12-26T00:08:02.009Z","count":0,"uniques":0},{"timestamp":"2025-12-27T00:08:04.810Z","count":0,"uniques":0},{"timestamp":"2025-12-28T00:08:19.019Z","count":0,"uniques":0},{"timestamp":"2025-12-29T00:08:20.308Z","count":0,"uniques":0},{"timestamp":"2025-12-30T00:08:13.590Z","count":0,"uniques":0},{"timestamp":"2025-12-31T00:08:09.153Z","count":0,"uniques":0},{"timestamp":"2026-01-01T00:08:46.963Z","count":0,"uniques":0},{"timestamp":"2026-01-02T00:08:02.911Z","count":0,"uniques":0},{"timestamp":"2026-01-03T00:08:00.398Z","count":0,"uniques":0},{"timestamp":"2026-01-04T00:08:25.053Z","count":0,"uniques":0},{"timestamp":"2026-01-05T00:08:25.573Z","count":0,"uniques":0},{"timestamp":"2026-01-06T00:08:46.665Z","count":0,"uniques":0},{"timestamp":"2026-01-07T00:07:07.713Z","count":0,"uniques":0},{"timestamp":"2026-01-08T00:08:15.759Z","count":0,"uniques":0},{"timestamp":"2026-01-09T00:07:53.758Z","count":0,"uniques":0}]
