[{"timestamp":"2026-04-27T00:18:24.068Z","count":0,"uniques":0},{"timestamp":"2026-04-28T00:22:20.387Z","count":0,"uniques":0},{"timestamp":"2026-04-29T00:23:17.355Z","count":0,"uniques":0},{"timestamp":"2026-04-30T00:23:28.197Z","count":0,"uniques":0},{"timestamp":"2026-05-01T00:22:59.060Z","count":0,"uniques":0},{"timestamp":"2026-05-02T00:22:14.763Z","count":0,"uniques":0},{"timestamp":"2026-05-03T00:20:50.424Z","count":0,"uniques":0},{"timestamp":"2026-05-04T00:22:14.986Z","count":0,"uniques":0}]
