[{"timestamp":"2022-06-11T00:41:34.301Z","count":0,"uniques":0},{"timestamp":"2022-06-12T00:41:40.591Z","count":0,"uniques":0},{"timestamp":"2022-06-13T00:45:42.903Z","count":0,"uniques":0},{"timestamp":"2022-06-14T00:49:36.979Z","count":0,"uniques":0},{"timestamp":"2022-06-15T00:43:48.686Z","count":0,"uniques":0},{"timestamp":"2022-06-16T00:41:04.288Z","count":0,"uniques":0},{"timestamp":"2022-06-17T00:36:24.868Z","count":0,"uniques":0},{"timestamp":"2022-06-18T00:42:05.874Z","count":0,"uniques":0}]
