[{"timestamp":"2022-11-18T00:00:00.000Z","count":25,"uniques":7},{"timestamp":"2022-11-19T00:00:00.000Z","count":12,"uniques":3},{"timestamp":"2022-11-20T00:00:00.000Z","count":4,"uniques":3},{"timestamp":"2022-11-21T00:00:00.000Z","count":20,"uniques":2},{"timestamp":"2022-11-22T00:00:00.000Z","count":42,"uniques":4},{"timestamp":"2022-11-23T00:00:00.000Z","count":1,"uniques":1},{"timestamp":"2022-11-24T00:00:00.000Z","count":7,"uniques":5},{"timestamp":"2022-11-25T00:38:55.971Z","count":0,"uniques":0}]
