[{"timestamp":"2023-11-01T00:00:00.000Z","count":920,"uniques":264},{"timestamp":"2023-11-02T00:00:00.000Z","count":1127,"uniques":362},{"timestamp":"2023-11-03T00:00:00.000Z","count":1012,"uniques":282},{"timestamp":"2023-11-04T00:00:00.000Z","count":741,"uniques":192},{"timestamp":"2023-11-05T00:00:00.000Z","count":878,"uniques":240},{"timestamp":"2023-11-06T00:00:00.000Z","count":1113,"uniques":312},{"timestamp":"2023-11-07T00:00:00.000Z","count":1339,"uniques":361},{"timestamp":"2023-11-08T00:04:18.554Z","count":0,"uniques":0}]
