[{"timestamp":"2024-08-13T00:00:00.000Z","count":1181,"uniques":397},{"timestamp":"2024-08-14T00:00:00.000Z","count":1258,"uniques":374},{"timestamp":"2024-08-15T00:00:00.000Z","count":1399,"uniques":399},{"timestamp":"2024-08-16T00:00:00.000Z","count":1176,"uniques":324},{"timestamp":"2024-08-17T00:00:00.000Z","count":997,"uniques":273},{"timestamp":"2024-08-18T00:00:00.000Z","count":1032,"uniques":304},{"timestamp":"2024-08-19T00:00:00.000Z","count":1163,"uniques":342},{"timestamp":"2024-08-20T00:05:11.656Z","count":0,"uniques":0}]
