[{"timestamp":"2024-08-26T00:00:00.000Z","count":1087,"uniques":363},{"timestamp":"2024-08-27T00:00:00.000Z","count":1334,"uniques":409},{"timestamp":"2024-08-28T00:00:00.000Z","count":1247,"uniques":395},{"timestamp":"2024-08-29T00:00:00.000Z","count":1974,"uniques":539},{"timestamp":"2024-08-30T00:00:00.000Z","count":1402,"uniques":388},{"timestamp":"2024-08-31T00:00:00.000Z","count":1073,"uniques":315},{"timestamp":"2024-09-01T00:00:00.000Z","count":925,"uniques":267},{"timestamp":"2024-09-02T00:05:21.137Z","count":0,"uniques":0}]
