[{"timestamp":"2021-10-24T00:00:00.000Z","count":307,"uniques":68},{"timestamp":"2021-10-25T00:00:00.000Z","count":536,"uniques":80},{"timestamp":"2021-10-26T00:00:00.000Z","count":453,"uniques":88},{"timestamp":"2021-10-27T00:00:00.000Z","count":433,"uniques":103},{"timestamp":"2021-10-28T00:00:00.000Z","count":513,"uniques":187},{"timestamp":"2021-10-29T00:00:00.000Z","count":323,"uniques":150},{"timestamp":"2021-10-30T00:00:00.000Z","count":109,"uniques":50},{"timestamp":"2021-10-31T00:00:00.000Z","count":104,"uniques":31}]
