[{"timestamp":"2026-03-14T00:00:00.000Z","count":252,"uniques":149},{"timestamp":"2026-03-15T00:00:00.000Z","count":323,"uniques":135},{"timestamp":"2026-03-16T00:00:00.000Z","count":429,"uniques":234},{"timestamp":"2026-03-17T00:00:00.000Z","count":408,"uniques":262},{"timestamp":"2026-03-18T00:00:00.000Z","count":425,"uniques":259},{"timestamp":"2026-03-19T00:00:00.000Z","count":503,"uniques":309},{"timestamp":"2026-03-20T00:09:18.572Z","count":0,"uniques":0},{"timestamp":"2026-03-21T00:08:43.210Z","count":0,"uniques":0}]
