[{"timestamp":"2023-01-25T00:00:00.000Z","count":480,"uniques":249},{"timestamp":"2023-01-26T00:00:00.000Z","count":487,"uniques":270},{"timestamp":"2023-01-27T00:00:00.000Z","count":689,"uniques":315},{"timestamp":"2023-01-28T00:00:00.000Z","count":390,"uniques":213},{"timestamp":"2023-01-29T00:00:00.000Z","count":378,"uniques":191},{"timestamp":"2023-01-30T00:00:00.000Z","count":528,"uniques":256},{"timestamp":"2023-01-31T00:00:00.000Z","count":652,"uniques":330},{"timestamp":"2023-02-01T00:42:28.282Z","count":0,"uniques":0}]
