[{"timestamp":"2026-07-02T00:00:00.000Z","count":307,"uniques":218},{"timestamp":"2026-07-03T00:00:00.000Z","count":480,"uniques":317},{"timestamp":"2026-07-04T00:00:00.000Z","count":473,"uniques":255},{"timestamp":"2026-07-05T00:00:00.000Z","count":391,"uniques":247},{"timestamp":"2026-07-06T00:00:00.000Z","count":371,"uniques":230},{"timestamp":"2026-07-07T00:00:00.000Z","count":359,"uniques":230},{"timestamp":"2026-07-08T01:29:44.726Z","count":0,"uniques":0},{"timestamp":"2026-07-09T01:52:07.634Z","count":0,"uniques":0}]
