[{"timestamp":"2025-07-31T00:00:00.000Z","count":487,"uniques":247},{"timestamp":"2025-08-01T00:00:00.000Z","count":393,"uniques":206},{"timestamp":"2025-08-02T00:00:00.000Z","count":296,"uniques":164},{"timestamp":"2025-08-03T00:00:00.000Z","count":332,"uniques":164},{"timestamp":"2025-08-04T00:00:00.000Z","count":385,"uniques":249},{"timestamp":"2025-08-05T00:00:00.000Z","count":619,"uniques":340},{"timestamp":"2025-08-06T00:00:00.000Z","count":496,"uniques":263},{"timestamp":"2025-08-07T00:06:53.520Z","count":0,"uniques":0}]
