[{"timestamp":"2026-05-29T00:00:00.000Z","count":391,"uniques":279},{"timestamp":"2026-05-30T00:00:00.000Z","count":397,"uniques":262},{"timestamp":"2026-05-31T00:00:00.000Z","count":441,"uniques":264},{"timestamp":"2026-06-01T00:00:00.000Z","count":319,"uniques":233},{"timestamp":"2026-06-02T00:00:00.000Z","count":247,"uniques":188},{"timestamp":"2026-06-03T00:00:00.000Z","count":263,"uniques":181},{"timestamp":"2026-06-04T00:37:08.216Z","count":0,"uniques":0},{"timestamp":"2026-06-05T00:28:53.047Z","count":0,"uniques":0}]
