[{"timestamp":"2023-02-04T00:00:00.000Z","count":341,"uniques":193},{"timestamp":"2023-02-05T00:00:00.000Z","count":350,"uniques":201},{"timestamp":"2023-02-06T00:00:00.000Z","count":475,"uniques":259},{"timestamp":"2023-02-07T00:00:00.000Z","count":410,"uniques":248},{"timestamp":"2023-02-08T00:00:00.000Z","count":440,"uniques":276},{"timestamp":"2023-02-09T00:00:00.000Z","count":735,"uniques":274},{"timestamp":"2023-02-10T00:00:00.000Z","count":512,"uniques":291},{"timestamp":"2023-02-11T00:33:37.320Z","count":0,"uniques":0}]
