[{"timestamp":"2023-12-05T00:00:00.000Z","count":3060,"uniques":747},{"timestamp":"2023-12-06T00:00:00.000Z","count":2208,"uniques":520},{"timestamp":"2023-12-07T00:00:00.000Z","count":1601,"uniques":453},{"timestamp":"2023-12-08T00:00:00.000Z","count":1237,"uniques":338},{"timestamp":"2023-12-09T00:00:00.000Z","count":1003,"uniques":292},{"timestamp":"2023-12-10T00:00:00.000Z","count":977,"uniques":286},{"timestamp":"2023-12-11T00:00:00.000Z","count":1296,"uniques":409},{"timestamp":"2023-12-12T00:04:27.421Z","count":0,"uniques":0}]
