[{"timestamp":"2023-03-21T00:00:00.000Z","count":7,"uniques":3},{"timestamp":"2023-03-22T00:00:00.000Z","count":4,"uniques":3},{"timestamp":"2023-03-23T00:00:00.000Z","count":3,"uniques":2},{"timestamp":"2023-03-24T00:00:00.000Z","count":1,"uniques":1},{"timestamp":"2023-03-25T00:00:00.000Z","count":2,"uniques":2},{"timestamp":"2023-03-26T00:00:00.000Z","count":3,"uniques":2},{"timestamp":"2023-03-27T00:00:00.000Z","count":3,"uniques":2},{"timestamp":"2023-03-28T00:38:35.377Z","count":0,"uniques":0}]
