[{"timestamp":"2024-11-02T00:00:00.000Z","count":2,"uniques":2},{"timestamp":"2024-11-03T00:00:00.000Z","count":12,"uniques":1},{"timestamp":"2024-11-04T00:00:00.000Z","count":1,"uniques":1},{"timestamp":"2024-11-05T00:00:00.000Z","count":4,"uniques":4},{"timestamp":"2024-11-06T00:00:00.000Z","count":16,"uniques":5},{"timestamp":"2024-11-07T00:00:00.000Z","count":16,"uniques":5},{"timestamp":"2024-11-08T00:00:00.000Z","count":1,"uniques":1},{"timestamp":"2024-11-09T00:06:28.717Z","count":0,"uniques":0}]
