[{"timestamp":"2021-12-15T00:00:00.000Z","count":146,"uniques":43},{"timestamp":"2021-12-16T00:00:00.000Z","count":146,"uniques":47},{"timestamp":"2021-12-17T00:00:00.000Z","count":174,"uniques":68},{"timestamp":"2021-12-18T00:00:00.000Z","count":113,"uniques":29},{"timestamp":"2021-12-19T00:00:00.000Z","count":118,"uniques":31},{"timestamp":"2021-12-20T00:00:00.000Z","count":175,"uniques":48},{"timestamp":"2021-12-21T00:00:00.000Z","count":240,"uniques":52},{"timestamp":"2021-12-22T00:00:00.000Z","count":167,"uniques":43}]
