[{"timestamp":"2026-07-06T00:00:00.000Z","count":12,"uniques":8},{"timestamp":"2026-07-07T00:00:00.000Z","count":4,"uniques":3},{"timestamp":"2026-07-08T00:00:00.000Z","count":3,"uniques":3},{"timestamp":"2026-07-09T00:00:00.000Z","count":5,"uniques":5},{"timestamp":"2026-07-10T00:00:00.000Z","count":9,"uniques":6},{"timestamp":"2026-07-11T00:00:00.000Z","count":15,"uniques":8},{"timestamp":"2026-07-12T01:41:10.447Z","count":0,"uniques":0},{"timestamp":"2026-07-13T01:44:06.204Z","count":0,"uniques":0}]
