[{"timestamp":"2025-01-22T00:00:00.000Z","count":58,"uniques":28},{"timestamp":"2025-01-23T00:00:00.000Z","count":91,"uniques":29},{"timestamp":"2025-01-24T00:00:00.000Z","count":42,"uniques":21},{"timestamp":"2025-01-25T00:00:00.000Z","count":78,"uniques":26},{"timestamp":"2025-01-26T00:00:00.000Z","count":38,"uniques":15},{"timestamp":"2025-01-27T00:00:00.000Z","count":103,"uniques":26},{"timestamp":"2025-01-28T00:00:00.000Z","count":115,"uniques":28},{"timestamp":"2025-01-29T00:04:06.928Z","count":0,"uniques":0}]
