[{"timestamp":"2023-08-01T00:00:00.000Z","count":346,"uniques":48},{"timestamp":"2023-08-02T00:00:00.000Z","count":88,"uniques":32},{"timestamp":"2023-08-03T00:00:00.000Z","count":203,"uniques":43},{"timestamp":"2023-08-04T00:00:00.000Z","count":259,"uniques":40},{"timestamp":"2023-08-05T00:00:00.000Z","count":81,"uniques":17},{"timestamp":"2023-08-06T00:00:00.000Z","count":74,"uniques":25},{"timestamp":"2023-08-07T00:00:00.000Z","count":151,"uniques":38},{"timestamp":"2023-08-08T00:03:18.134Z","count":0,"uniques":0}]
