[{"timestamp":"2024-10-30T00:00:00.000Z","count":75,"uniques":26},{"timestamp":"2024-10-31T00:00:00.000Z","count":43,"uniques":19},{"timestamp":"2024-11-01T00:00:00.000Z","count":85,"uniques":32},{"timestamp":"2024-11-02T00:00:00.000Z","count":47,"uniques":22},{"timestamp":"2024-11-03T00:00:00.000Z","count":47,"uniques":28},{"timestamp":"2024-11-04T00:00:00.000Z","count":67,"uniques":27},{"timestamp":"2024-11-05T00:00:00.000Z","count":98,"uniques":34},{"timestamp":"2024-11-06T00:04:17.252Z","count":0,"uniques":0}]
