[{"timestamp":"2025-02-11T00:00:00.000Z","count":2,"uniques":1},{"timestamp":"2025-02-12T00:00:00.000Z","count":5,"uniques":2},{"timestamp":"2025-02-13T00:00:00.000Z","count":5,"uniques":2},{"timestamp":"2025-02-14T00:00:00.000Z","count":2,"uniques":2},{"timestamp":"2025-02-15T00:04:33.612Z","count":0,"uniques":0},{"timestamp":"2025-02-16T00:00:00.000Z","count":7,"uniques":6},{"timestamp":"2025-02-17T00:00:00.000Z","count":1,"uniques":1},{"timestamp":"2025-02-18T00:04:47.750Z","count":0,"uniques":0}]
