[{"timestamp":"2022-08-01T00:50:49.076Z","count":0,"uniques":0},{"timestamp":"2022-08-02T00:44:48.161Z","count":0,"uniques":0},{"timestamp":"2022-08-03T00:47:47.541Z","count":0,"uniques":0},{"timestamp":"2022-08-04T00:45:55.798Z","count":0,"uniques":0},{"timestamp":"2022-08-05T00:49:54.491Z","count":0,"uniques":0},{"timestamp":"2022-08-06T00:41:13.238Z","count":0,"uniques":0},{"timestamp":"2022-08-07T00:46:30.645Z","count":0,"uniques":0},{"timestamp":"2022-08-08T00:39:24.495Z","count":0,"uniques":0},{"timestamp":"2022-08-09T00:48:38.069Z","count":0,"uniques":0},{"timestamp":"2022-08-10T00:41:20.988Z","count":0,"uniques":0},{"timestamp":"2022-08-11T00:42:45.282Z","count":0,"uniques":0},{"timestamp":"2022-08-12T00:40:34.700Z","count":0,"uniques":0},{"timestamp":"2022-08-13T00:39:21.118Z","count":0,"uniques":0},{"timestamp":"2022-08-14T00:43:21.172Z","count":0,"uniques":0},{"timestamp":"2022-08-15T00:00:00.000Z","count":1,"uniques":1},{"timestamp":"2022-08-16T00:49:32.962Z","count":0,"uniques":0},{"timestamp":"2022-08-17T00:00:00.000Z","count":1,"uniques":1},{"timestamp":"2022-08-18T00:00:00.000Z","count":1,"uniques":1},{"timestamp":"2022-08-19T00:45:40.366Z","count":0,"uniques":0},{"timestamp":"2022-08-20T00:00:00.000Z","count":1,"uniques":1},{"timestamp":"2022-08-21T00:40:28.979Z","count":0,"uniques":0},{"timestamp":"2022-08-22T00:44:07.307Z","count":0,"uniques":0},{"timestamp":"2022-08-23T00:52:34.530Z","count":0,"uniques":0},{"timestamp":"2022-08-24T00:45:37.160Z","count":0,"uniques":0},{"timestamp":"2022-08-25T00:53:15.391Z","count":0,"uniques":0},{"timestamp":"2022-08-26T00:45:54.441Z","count":0,"uniques":0},{"timestamp":"2022-08-27T00:39:51.258Z","count":0,"uniques":0},{"timestamp":"2022-08-28T00:47:13.318Z","count":0,"uniques":0},{"timestamp":"2022-08-29T00:00:00.000Z","count":2,"uniques":1},{"timestamp":"2022-08-30T00:53:35.048Z","count":0,"uniques":0},{"timestamp":"2022-08-31T00:55:16.303Z","count":0,"uniques":0}]
