[{"timestamp":"2023-08-26T00:04:42.148Z","count":0,"uniques":0},{"timestamp":"2023-08-27T00:05:13.690Z","count":0,"uniques":0},{"timestamp":"2023-08-28T00:04:58.585Z","count":0,"uniques":0},{"timestamp":"2023-08-29T00:05:08.899Z","count":0,"uniques":0},{"timestamp":"2023-08-30T00:00:00.000Z","count":11,"uniques":1},{"timestamp":"2023-08-31T00:04:52.333Z","count":0,"uniques":0},{"timestamp":"2023-09-01T00:00:00.000Z","count":1,"uniques":1},{"timestamp":"2023-09-02T00:04:41.073Z","count":0,"uniques":0}]
