[{"timestamp":"2022-11-25T00:39:46.894Z","count":0,"uniques":0},{"timestamp":"2022-11-26T00:35:48.051Z","count":0,"uniques":0},{"timestamp":"2022-11-27T00:43:22.044Z","count":0,"uniques":0},{"timestamp":"2022-11-28T00:36:50.124Z","count":0,"uniques":0},{"timestamp":"2022-11-29T00:40:12.080Z","count":0,"uniques":0},{"timestamp":"2022-11-30T00:00:00.000Z","count":26,"uniques":2},{"timestamp":"2022-12-01T00:43:45.221Z","count":0,"uniques":0},{"timestamp":"2022-12-02T00:36:34.359Z","count":0,"uniques":0}]
