[{"timestamp":"2026-04-14T00:00:00.000Z","count":3,"uniques":3},{"timestamp":"2026-04-15T00:00:00.000Z","count":4,"uniques":2},{"timestamp":"2026-04-16T00:00:00.000Z","count":10,"uniques":1},{"timestamp":"2026-04-17T00:00:00.000Z","count":2,"uniques":2},{"timestamp":"2026-04-18T00:00:00.000Z","count":4,"uniques":4},{"timestamp":"2026-04-19T00:00:00.000Z","count":2,"uniques":2},{"timestamp":"2026-04-20T00:00:00.000Z","count":1,"uniques":1},{"timestamp":"2026-04-21T00:00:00.000Z","count":3,"uniques":3},{"timestamp":"2026-04-22T00:15:31.798Z","count":0,"uniques":0},{"timestamp":"2026-04-23T00:20:24.121Z","count":0,"uniques":0},{"timestamp":"2026-04-24T00:00:00.000Z","count":5,"uniques":2},{"timestamp":"2026-04-25T00:00:00.000Z","count":2,"uniques":2},{"timestamp":"2026-04-26T00:00:00.000Z","count":3,"uniques":1},{"timestamp":"2026-04-27T00:00:00.000Z","count":1,"uniques":1},{"timestamp":"2026-04-28T00:21:57.533Z","count":0,"uniques":0},{"timestamp":"2026-04-29T00:00:00.000Z","count":1,"uniques":1},{"timestamp":"2026-04-30T00:00:00.000Z","count":4,"uniques":3},{"timestamp":"2026-05-01T00:00:00.000Z","count":3,"uniques":3},{"timestamp":"2026-05-02T00:00:00.000Z","count":3,"uniques":3},{"timestamp":"2026-05-03T00:00:00.000Z","count":2,"uniques":2},{"timestamp":"2026-05-04T00:00:00.000Z","count":1,"uniques":1},{"timestamp":"2026-05-05T00:22:43.325Z","count":0,"uniques":0},{"timestamp":"2026-05-06T00:00:00.000Z","count":1,"uniques":1},{"timestamp":"2026-05-07T00:22:08.840Z","count":0,"uniques":0},{"timestamp":"2026-05-08T00:22:17.460Z","count":0,"uniques":0},{"timestamp":"2026-05-09T00:00:00.000Z","count":2,"uniques":1},{"timestamp":"2026-05-10T00:22:36.774Z","count":0,"uniques":0},{"timestamp":"2026-05-11T00:00:00.000Z","count":1,"uniques":1},{"timestamp":"2026-05-12T00:00:00.000Z","count":4,"uniques":1},{"timestamp":"2026-05-13T00:26:00.095Z","count":0,"uniques":0},{"timestamp":"2026-05-14T00:27:39.460Z","count":0,"uniques":0}]
