[{"timestamp":"2025-10-17T00:00:00.000Z","count":2,"uniques":2},{"timestamp":"2025-10-18T00:00:00.000Z","count":3,"uniques":3},{"timestamp":"2025-10-19T00:00:00.000Z","count":1,"uniques":1},{"timestamp":"2025-10-20T00:00:00.000Z","count":1,"uniques":1},{"timestamp":"2025-10-21T00:00:00.000Z","count":2,"uniques":2},{"timestamp":"2025-10-22T00:00:00.000Z","count":4,"uniques":3},{"timestamp":"2025-10-23T00:00:00.000Z","count":4,"uniques":3},{"timestamp":"2025-10-24T00:06:33.598Z","count":0,"uniques":0}]
